{
    "Version": "1.2",
    "Data": {
        "Source": "c:\\users\\ga3\\desktop\\cart\\cart\\intermediate\\build\\win64\\unrealeditor\\inc\\cart\\uht\\movableobject.gen.cpp",
        "ProvidedModule": "",
        "PCH": "c:\\users\\ga3\\desktop\\cart\\cart\\intermediate\\build\\win64\\x64\\carteditor\\development\\unrealed\\sharedpch.unrealed.project.valapi.cpp20.h.pch",
        "Includes": [
            "c:\\users\\ga3\\desktop\\cart\\cart\\intermediate\\build\\win64\\x64\\unrealeditor\\development\\cart\\definitions.cart.h",
            "c:\\users\\ga3\\desktop\\cart\\cart\\source\\cart\\public\\movableobject.h",
            "c:\\users\\ga3\\desktop\\cart\\cart\\intermediate\\build\\win64\\unrealeditor\\inc\\cart\\uht\\movableobject.generated.h"
        ],
        "ImportedModules": [],
        "ImportedHeaderUnits": []
    }
}